hl7/__init__.py
hl7/_config.py
hl7/_from_hl7.py
hl7/_to_hl7.py
hl7/data/hl7v2.5.1.json
py_hl7-0.0.5.dist-info/METADATA
py_hl7-0.0.5.dist-info/WHEEL
py_hl7-0.0.5.dist-info/RECORD
