Metadata-Version: 2.1
Name: py-hl7
Version: 0.0.5
Summary: Converter for HL7 messages to and from multiple formats (Excel, CSV)
Home-page: https://github.com/Jan-PieterK/py-hl7
License: MIT
Keywords: hl7,health-level-seven,health care
Author: CISolutions B.V.
Author-email: info@cisolutions.nl
Requires-Python: >=3.9
Classifier: Environment :: Console
Classifier: License :: OSI Approved :: MIT License
Classifier: Operating System :: OS Independent
Classifier: Programming Language :: Python :: 3
Classifier: Programming Language :: Python :: 3.9
Classifier: Programming Language :: Python :: 3.10
Classifier: Programming Language :: Python :: 3.11
Classifier: Topic :: Software Development :: Documentation
Classifier: Topic :: Software Development :: Libraries :: Python Modules
Classifier: Topic :: Software Development :: Quality Assurance
Requires-Dist: openpyxl (==3.1.2)
Project-URL: Repository, https://github.com/Jan-PieterK/py-hl7
